[
    {
        "date": "2015-04-06",
        "count": 890,
        "percent": 0.76
    }, {
        "date": "2015-04-07",
        "count": 1048,
        "percent": 0.73
    }, {
        "date": "2015-04-08",
        "count": 935,
        "percent": 0.78
    }, {
        "date": "2015-04-09",
        "count": 857,
        "percent": 0.73
    }, {
        "date": "2015-04-10",
        "count": 710,
        "percent": 0.73
    }, {
        "date": "2015-04-11",
        "count": 914,
        "percent": 0.71
    }, {
        "date": "2015-04-12",
        "count": 779,
        "percent": 0.75
    }, {
        "date": "2015-04-13",
        "count": 797,
        "percent": 0.76
    }, {
        "date": "2015-04-14",
        "count": 839,
        "percent": 0.72
    }, {
        "date": "2015-04-15",
        "count": 707,
        "percent": 0.72
    }, {
        "date": "2015-04-16",
        "count": 3642,
        "percent": 0.75
    }, {
        "date": "2015-04-17",
        "count": 1890,
        "percent": 0.74
    }, {
        "date": "2015-04-18",
        "count": 290,
        "percent": 0.70
    }, {
        "date": "2015-04-19",
        "count": 650,
        "percent": 0.78
    }, {
        "date": "2015-04-20",
        "count": 890,
        "percent": 0.75
    }, {
        "date": "2015-04-21",
        "count": 890,
        "percent": 0.77
    }, {
        "date": "2015-04-22",
        "count": 890,
        "percent": 0.75
    }, {
        "date": "2015-04-23",
        "count": 890,
        "percent": 0.77
    }, {
        "date": "2015-04-24",
        "count": 890,
        "percent": 0.75
    }, {
        "date": "2015-04-25",
        "count": 890,
        "percent": 0.77
    }, {
        "date": "2015-04-26",
        "count": 890,
        "percent": 0.80
    }, {
        "date": "2015-04-27",
        "count": 890,
        "percent": 0.73
    }
]